cloci/main.py
cloci/lib/__init__.py
cloci/lib/evo_conco.py
cloci/lib/generate_nulls.py
cloci/lib/hgp2hgx.py
cloci/lib/hgx2hlgs.py
cloci/lib/input_parsing.py
cloci/lib/output_data.py
cloci/lib/treecalcs.py
cloci/tools/__init__.py
cloci/tools/cloci2annotate.py
cloci/tools/cloci2enrich.py
cloci/tools/cloci2stats.py
cloci/tools/hg2hg_net.py
cloci/tools/hlg2biofile.py
cloci/tools/hlg2heatmap.py
cloci/tools/hlg2hlg_net.py
cloci-0.3.0.dist-info/LICENSE
cloci-0.3.0.dist-info/METADATA
cloci-0.3.0.dist-info/WHEEL
cloci-0.3.0.dist-info/entry_points.txt
cloci-0.3.0.dist-info/top_level.txt
cloci-0.3.0.dist-info/RECORD
