Metadata-Version: 2.1
Name: cloci
Version: 0.3.0
Summary: Co-occurrence Locus and Orthologous Cluster Identifier
Author-email: Zachary Konkel <konkelzach@protonmail.com>
License: GNU AFFERO GENERAL PUBLIC LICENSE
Project-URL: Homepage, https://github.com/xonq/cloci
Project-URL: Bug Tracker, https://github.com/xonq/cloci/issues
Classifier: Programming Language :: Python :: 3
Classifier: License :: OSI Approved :: GNU Lesser General Public License v3 or later (LGPLv3+)
Classifier: Operating System :: POSIX :: Linux
Requires-Python: <4,>=3.0
License-File: LICENSE
Requires-Dist: mycotools
Requires-Dist: cogent3
Requires-Dist: tqdm
Requires-Dist: plotly
